MANIFEST.in
README.rst
TESTING.txt
requirements.txt
setup.py
pyoos/__init__.py
pyoos.egg-info/PKG-INFO
pyoos.egg-info/SOURCES.txt
pyoos.egg-info/dependency_links.txt
pyoos.egg-info/requires.txt
pyoos.egg-info/top_level.txt
pyoos/collectors/__init__.py
pyoos/collectors/collector.py
pyoos/collectors/awc/__init__.py
pyoos/collectors/awc/awc_rest.py
pyoos/collectors/coops/__init__.py
pyoos/collectors/coops/coops_sos.py
pyoos/collectors/hads/__init__.py
pyoos/collectors/hads/hads.py
pyoos/collectors/ioos/__init__.py
pyoos/collectors/ioos/swe_sos.py
pyoos/collectors/ndbc/__init__.py
pyoos/collectors/ndbc/ndbc_sos.py
pyoos/collectors/nerrs/__init__.py
pyoos/collectors/nerrs/nerrs_soap.py
pyoos/collectors/usgs/__init__.py
pyoos/collectors/usgs/usgs_rest.py
pyoos/collectors/wqp/__init__.py
pyoos/collectors/wqp/wqp_rest.py
pyoos/parsers/__init__.py
pyoos/parsers/awc.py
pyoos/parsers/hads.py
pyoos/parsers/nerrs.py
pyoos/parsers/waterml.py
pyoos/parsers/ioos/__init__.py
pyoos/parsers/ioos/describe_sensor.py
pyoos/parsers/ioos/get_observation.py
pyoos/parsers/ioos/one/__init__.py
pyoos/parsers/ioos/one/describe_sensor.py
pyoos/parsers/ioos/one/get_observation.py
pyoos/parsers/ioos/one/timeseries.py
pyoos/parsers/ioos/one/timeseries_profile.py
pyoos/parsers/wqx/__init__.py
pyoos/parsers/wqx/wqx_outbound.py
pyoos/utils/__init__.py
pyoos/utils/asatime.py
pyoos/utils/dataorg.py
pyoos/utils/etree.py
tests/__init__.py
tests/utils.py
tests/collectors/__init__.py
tests/collectors/test_awc_rest.py
tests/collectors/test_collector.py
tests/collectors/test_coops_sos.py
tests/collectors/test_hads.py
tests/collectors/test_ndbc_sos.py
tests/collectors/test_nerrs.py
tests/collectors/test_usgs.py
tests/collectors/test_wqp.py