Metadata-Version: 1.1
Name: pyoos
Version: 0.8.4
Summary: A Python library for collecting Met/Ocean observations
Home-page: https://github.com/ioos/pyoos.git
Author: Kyle Wilcox
Author-email: kyle@axiomdatascience.com
License: GPLv3
Platform: UNKNOWN
Classifier: Development Status :: 3 - Alpha
Classifier: Intended Audience :: Developers
Classifier: Intended Audience :: Science/Research
Classifier: License :: OSI Approved :: GNU General Public License v3 (GPLv3)
Classifier: Operating System :: POSIX :: Linux
Classifier: Programming Language :: Python
Classifier: Topic :: Scientific/Engineering
